geedim/__init__.py
geedim/cli.py
geedim/collection.py
geedim/download.py
geedim/enums.py
geedim/image.py
geedim/mask.py
geedim/medoid.py
geedim/py.typed
geedim/schema.py
geedim/stac.py
geedim/tile.py
geedim/utils.py
geedim/version.py
geedim-2.0.0.dist-info/licenses/LICENSE
geedim-2.0.0.dist-info/METADATA
geedim-2.0.0.dist-info/WHEEL
geedim-2.0.0.dist-info/entry_points.txt
geedim-2.0.0.dist-info/top_level.txt
geedim-2.0.0.dist-info/RECORD
