Metadata-Version: 2.4
Name: geedim
Version: 2.0.0
Summary: Export and cloud mask Google Earth Engine imagery.
Author: Leftfield Geospatial
Project-URL: Homepage, https://github.com/leftfield-geospatial/geedim
Project-URL: Documentation, https://geedim.readthedocs.org
Project-URL: Source, https://github.com/leftfield-geospatial/geedim
Project-URL: Changelog, https://github.com/leftfield-geospatial/geedim/releases
Project-URL: Issues, https://github.com/leftfield-geospatial/geedim/issues
Keywords: earth engine,image,export,geotiff,xarray,numpy,cloud,mask
Classifier: Programming Language :: Python :: 3
Classifier: License :: OSI Approved :: Apache Software License
Classifier: Operating System :: OS Independent
Requires-Python: >=3.11
License-File: LICENSE
Requires-Dist: numpy>=1.19
Requires-Dist: rasterio>=1.3.8
Requires-Dist: click>=8
Requires-Dist: tqdm>=4.6
Requires-Dist: earthengine-api>=0.1.379
Requires-Dist: tabulate>=0.9
Requires-Dist: fsspec>=2025.2
Requires-Dist: aiohttp>=3.11
Provides-Extra: xarray
Requires-Dist: xarray; extra == "xarray"
Dynamic: license-file
